Metadata-Version: 1.1
Name: terra-python-plugin
Version: 1.0
Summary: A python plugin to send data(json) from any data platform to a connected API.
Home-page: https://D-Scipher@bitbucket.org/terragonengineering/kafka-python-plugin.git
Author: Timothy
Author-email: adeyeyetimothy33@gmail.com
License: MIT
Platform: UNKNOWN
Classifier: Development Status :: 3 - Alpha
Classifier: Intended Audience :: Developers
Classifier: Topic :: Software Development :: Build Tools
Classifier: License :: OSI Approved :: MIT License
Classifier: Programming Language :: Python :: 3
Classifier: Programming Language :: Python :: 3.4
Classifier: Programming Language :: Python :: 3.5
Classifier: Programming Language :: Python :: 3.6
